nzb/__init__.py
nzb/_core.py
nzb/_exceptions.py
nzb/_models.py
nzb/_parsers.py
nzb/_subparsers.py
nzb/_utils.py
nzb/py.typed
nzb-0.6.0.dist-info/METADATA
nzb-0.6.0.dist-info/WHEEL
nzb-0.6.0.dist-info/licenses/LICENSE
nzb-0.6.0.dist-info/RECORD
