Metadata-Version: 2.4
Name: nzb
Version: 0.6.0
Summary: A spec compliant parser and meta editor for NZB files.
Project-URL: Documentation, https://ravencentric.cc/nzb/
Project-URL: Repository, https://github.com/Ravencentric/nzb
Author-email: Ravencentric <me@ravencentric.cc>
License-Expression: MIT
License-File: LICENSE
Keywords: nzb,parser,usenet
Classifier: Operating System :: OS Independent
Classifier: Programming Language :: Python :: 3.10
Classifier: Programming Language :: Python :: 3.11
Classifier: Programming Language :: Python :: 3.12
Classifier: Programming Language :: Python :: 3.13
Classifier: Programming Language :: Python :: 3.14
Classifier: Typing :: Typed
Requires-Python: >=3.10
